__init__.py
cli.py
main.py
mermaid_agent.py
core/__init__.py
core/common_types.py
core/utils.py
tools/__init__.py
tools/desribe_diagram.py
tools/detect_intent.py
tools/extract_mermaid_code.py
tools/generate_context.py
tools/generate_diagram.py
tools/router.py
tools/tools_wrapper.py
tools/transform_diagram.py
tools/validators.py
mermaid_flow-0.1.0.dist-info/METADATA
mermaid_flow-0.1.0.dist-info/WHEEL
mermaid_flow-0.1.0.dist-info/entry_points.txt
mermaid_flow-0.1.0.dist-info/top_level.txt
mermaid_flow-0.1.0.dist-info/RECORD
