Metadata-Version: 2.4
Name: mermaid-flow
Version: 0.1.0
Summary: Mermaid diagram agent: generate, describe, transform, validate.
Author: Thanos Zikas
License: MIT
Project-URL: Homepage, https://github.com/zthanos/mermaid-flow
Project-URL: Issues, https://github.com/zthanos/mermaid-flow/issues
Requires-Python: >=3.12
Requires-Dist: beautifulsoup4>=4.14.2
Requires-Dist: dotenv>=0.9.9
Requires-Dist: gradio>=5.23.1
Requires-Dist: ipykernel>=7.1.0
Requires-Dist: ipython>=9.6.0
Requires-Dist: langchain>=1.0.3
Requires-Dist: langchain-community>=0.4.1
Requires-Dist: langchain-core>=1.0.2
Requires-Dist: langchain-openai>=1.0.1
Requires-Dist: langgraph>=1.0.2
Requires-Dist: pip>=25.3
Requires-Dist: pydantic>=2.12.3
Requires-Dist: requests>=2.32.5
